osier/__init__.py
osier/equations.py
osier/tech_library.py
osier/technology.py
osier/utils.py
osier/models/__init__.py
osier/models/capacity_expansion.py
osier/models/deap_runner.py
osier/models/dispatch.py
osier/models/logic_dispatch.py
osier/models/model.py
osier-0.4.2.dist-info/licenses/LICENSE
osier-0.4.2.dist-info/METADATA
osier-0.4.2.dist-info/WHEEL
osier-0.4.2.dist-info/top_level.txt
osier-0.4.2.dist-info/RECORD
