Metadata-Version: 2.4
Name: osier
Version: 0.4.2
Summary: osier: A justice oriented energy system optimization tool
Author-email: Sam Dotson <samgdotson@gmail.com>
Maintainer-email: Sam Dotson <samgdotson@gmail.com>
License: BSD 3-Clause License
Project-URL: Homepage, https://osier.readthedocs.io
Project-URL: Repository, https://github.com/arfc/osier
Project-URL: Issues, https://github.com/arfc/osier/issues
Keywords: energy systems,optimization,multi-objective,justice,multi-criteria decision
Classifier: Development Status :: 3 - Alpha
Classifier: Intended Audience :: Science/Research
Classifier: Programming Language :: Python :: 3.9
Classifier: Programming Language :: Python :: 3.10
Classifier: Programming Language :: Python :: 3.11
Classifier: Programming Language :: Python :: 3.12
Classifier: Environment :: Console
Classifier: Natural Language :: English
Classifier: Operating System :: OS Independent
Requires-Python: >=3.9
License-File: LICENSE
Requires-Dist: numpy
Requires-Dist: pandas
Requires-Dist: scipy
Requires-Dist: matplotlib
Requires-Dist: pytest
Requires-Dist: pytest-cov
Requires-Dist: dill
Requires-Dist: openpyxl
Requires-Dist: nrelpy
Requires-Dist: unyt
Requires-Dist: pymoo
Requires-Dist: pyentrp
Requires-Dist: deap
Requires-Dist: pyomo
Requires-Dist: toml
Provides-Extra: doc
Requires-Dist: sphinx>=5.1; extra == "doc"
Requires-Dist: sphinx-autobuild; extra == "doc"
Requires-Dist: myst-parser; extra == "doc"
Requires-Dist: sphinx_design; extra == "doc"
Requires-Dist: sphinx-autodoc-typehints; extra == "doc"
Requires-Dist: numpydoc; extra == "doc"
Requires-Dist: pydata_sphinx_theme; extra == "doc"
Requires-Dist: nbsphinx; extra == "doc"
Requires-Dist: pandoc; extra == "doc"
Requires-Dist: nbsphinx-link; extra == "doc"
Dynamic: license-file
